rgsync/Connectors/__init__.py
rgsync/Connectors/cql_connector.py
rgsync/Connectors/mongo_connector.py
rgsync/Connectors/redis_connector.py
rgsync/Connectors/simple_hash_connector.py
rgsync/Connectors/sql_connectors.py
rgsync/__init__.py
rgsync/common.py
rgsync/redis_gears_write_behind.py
rgsync-1.2.0.dist-info/LICENSE
rgsync-1.2.0.dist-info/WHEEL
rgsync-1.2.0.dist-info/METADATA
rgsync-1.2.0.dist-info/RECORD
