Metadata-Version: 2.1
Name: rgsync
Version: 1.2.0
Summary: RedisGears synchronization recipe
License: BSD-3-Clause
Keywords: redis,redisgears,writebehind
Author: Redis OSS
Author-email: oss@redis.com
Requires-Python: >=3.6.2,<4.0.0
Classifier: Development Status :: 5 - Production/Stable
Classifier: Intended Audience :: Developers
Classifier: License :: OSI Approved :: BSD License
Classifier: Operating System :: OS Independent
Classifier: Programming Language :: Python
Classifier: Programming Language :: Python :: 3
Classifier: Programming Language :: Python :: 3.10
Classifier: Programming Language :: Python :: 3.6
Classifier: Programming Language :: Python :: 3.7
Classifier: Programming Language :: Python :: 3.8
Classifier: Programming Language :: Python :: 3.9
Classifier: Topic :: Database
Requires-Dist: SQLAlchemy (==1.4.35)
Requires-Dist: pymongo (==4.1.1)
Requires-Dist: redis (>=4.2.0,<5.0.0)
